sysmetrics/__init__.py
sysmetrics/process.py
sysmetrics/sys.py
sysmetrics-0.0.1.dist-info/METADATA
sysmetrics-0.0.1.dist-info/WHEEL
sysmetrics-0.0.1.dist-info/top_level.txt
sysmetrics-0.0.1.dist-info/RECORD
