Metadata-Version: 2.1
Name: sysmetrics
Version: 0.0.1
Summary: The System Performance package provides tools to benchmark and visualize the performance of your system and specific processes over time.
Author: ROHIT CHOUHAN
Author-email: rohit170590@gmail.com
